LICENSE
MANIFEST.in
README.md
setup.py
django_volt_admin.egg-info/PKG-INFO
django_volt_admin.egg-info/SOURCES.txt
django_volt_admin.egg-info/dependency_links.txt
django_volt_admin.egg-info/requires.txt
django_volt_admin.egg-info/top_level.txt
volt/__init__.py
volt/admin.py
volt/apps.py
volt/iam.py
volt/models.py
volt/tests.py
volt/views.py
volt/migrations/__init__.py
volt/static/.DS_Store
volt/static/admin/css/autocomplete.css
volt/static/admin/css/base.css
volt/static/admin/css/changelists.css
volt/static/admin/css/dashboard.css
volt/static/admin/css/fonts.css
volt/static/admin/css/forms.css
volt/static/admin/css/login.css
volt/static/admin/css/nav_sidebar.css
volt/static/admin/css/reset.css
volt/static/admin/css/responsive.css
volt/static/admin/css/responsive_rtl.css
volt/static/admin/css/rtl.css
volt/static/admin/css/widgets.css
volt/static/admin/css/vendor/select2/LICENSE-SELECT2.md
volt/static/admin/css/vendor/select2/select2.css
volt/static/admin/css/vendor/select2/select2.min.css
volt/static/admin/fonts/LICENSE.txt
volt/static/admin/fonts/README.txt
volt/static/admin/fonts/Roboto-Bold-webfont.woff
volt/static/admin/fonts/Roboto-Light-webfont.woff
volt/static/admin/fonts/Roboto-Regular-webfont.woff
volt/static/admin/img/LICENSE
volt/static/admin/img/README.txt
volt/static/admin/img/calendar-icons.svg
volt/static/admin/img/icon-addlink.svg
volt/static/admin/img/icon-alert.svg
volt/static/admin/img/icon-calendar.svg
volt/static/admin/img/icon-changelink.svg
volt/static/admin/img/icon-clock.svg
volt/static/admin/img/icon-deletelink.svg
volt/static/admin/img/icon-no.svg
volt/static/admin/img/icon-unknown-alt.svg
volt/static/admin/img/icon-unknown.svg
volt/static/admin/img/icon-viewlink.svg
volt/static/admin/img/icon-yes.svg
volt/static/admin/img/inline-delete.svg
volt/static/admin/img/search.svg
volt/static/admin/img/selector-icons.svg
volt/static/admin/img/sorting-icons.svg
volt/static/admin/img/tooltag-add.svg
volt/static/admin/img/tooltag-arrowright.svg
volt/static/admin/img/gis/move_vertex_off.svg
volt/static/admin/img/gis/move_vertex_on.svg
volt/static/admin/js/SelectBox.js
volt/static/admin/js/SelectFilter2.js
volt/static/admin/js/actions.js
