Metadata-Version: 2.1
Name: django-volt-admin
Version: 1.0.1
Summary: Django admin implementation of volt admin dashboard
Home-page: https://github.com/adams-okode/django-volt-admin
Author: Adams Okode
Author-email: adamsokode@gmail.com
License: MIT
Platform: UNKNOWN
Classifier: Environment :: Web Environment
Classifier: Framework :: Django
Classifier: Framework :: Django :: 2.2
Classifier: Intended Audience :: Developers
Classifier: License :: OSI Approved :: BSD License
Classifier: Operating System :: OS Independent
Classifier: Programming Language :: Python
Classifier: Programming Language :: Python :: 3.6
Classifier: Programming Language :: Python :: 3.7
Classifier: Programming Language :: Python :: 3.8
Classifier: Programming Language :: Python :: 3.9
Provides-Extra: lint
Provides-Extra: dev
License-File: LICENSE
